dynamicObjInfra/__init__.py
dynamicObjInfra/baseObj.py
dynamicObjInfra/dbClient.py
dynamicObjInfra/debug.py
dynamicObjInfra/doi_logProvider.py
dynamicObjInfra/enums.py
dynamicObjInfra/eventsStream.py
dynamicObjInfra/redisClient.py
dynamicObjInfra/singleton.py
dynamicObjInfra/translations.py
dynamicObjInfra/validators.py
dynamicObjInfra/utils/__init__.py
dynamicObjInfra/utils/env.py
dynamicObjInfra/utils/indexing.py
dynamicObjInfra/utils/parser.py
dynamicobjinfra-0.3.28.dist-info/METADATA
dynamicobjinfra-0.3.28.dist-info/WHEEL
dynamicobjinfra-0.3.28.dist-info/top_level.txt
dynamicobjinfra-0.3.28.dist-info/RECORD
