Metadata-Version: 2.4
Name: dynamicObjInfra
Version: 0.3.28
Summary: A reusable infrastructure package for data handling
Author-email: Shaul Ben Maor <shaul@claro.one>
License: MIT
Project-URL: Bug Tracker, https://github.com/Shaulbm/dynamicObjInfra/issues
Project-URL: Documentation, https://github.com/Shaulbm/dynamicObjInfra
Project-URL: Source Code, https://github.com/Shaulbm/dynamicObjInfra
Requires-Python: >=3.7
Requires-Dist: pydantic
Requires-Dist: redis
Requires-Dist: pymongo
